signed_urls/__init__.py
signed_urls/sign.py
signed_urls/utils.py
signed_urls/validators.py
signed_urls/verify.py
signed_urls-0.1.0.dist-info/licenses/LICENSE
signed_urls-0.1.0.dist-info/METADATA
signed_urls-0.1.0.dist-info/WHEEL
signed_urls-0.1.0.dist-info/top_level.txt
signed_urls-0.1.0.dist-info/RECORD
