Metadata-Version: 2.4
Name: signed-urls
Version: 0.1.0
Summary: Sign and verify URLs using HMAC for secure temporary access.
Author-email: Vitalija Alisauskaite <v.alishauskaite@gmail.com>
Project-URL: Homepage, https://github.com/alv2017/signed-urls
Keywords: signed-urls,hmac,url-signing,url-verification,temporary-access
Classifier: License :: OSI Approved :: MIT License
Classifier: Programming Language :: Python
Classifier: Programming Language :: Python :: 3
Requires-Python: <3.15,>=3.12
License-File: LICENSE
Dynamic: license-file
